is_it_slop-0.4.0.dist-info/METADATA
is_it_slop-0.4.0.dist-info/WHEEL
is_it_slop/__init__.py
is_it_slop/_internal.py
is_it_slop/_is_it_slop_rust_bindings.cpython-312-darwin.so
is_it_slop/py.typed
is_it_slop-0.4.0.dist-info/RECORD
