Metadata-Version: 2.4
Name: is-it-slop
Version: 0.4.0
Summary: Detecting AI generated text using statistical ML models and TF-IDF vectorization
Author-email: SamBroomy <36888606+SamBroomy@users.noreply.github.com>
Requires-Python: >=3.11
